compass/__init__.py
compass/api_client/__init__.py
compass/api_client/api_client.py
compass/api_client/api_response.py
compass/api_client/configuration.py
compass/api_client/exceptions.py
compass/api_client/py.typed
compass/api_client/rest.py
compass/api_client/api/__init__.py
compass/api_client/api/aave_v3_api.py
compass/api_client/api/aerodrome_api.py
compass/api_client/api/aerodrome_basic_api.py
compass/api_client/api/aerodrome_slipstream_api.py
compass/api_client/api/default_api.py
compass/api_client/api/multicall_api.py
compass/api_client/api/others_api.py
compass/api_client/api/token_api.py
compass/api_client/api/transaction_batching_api.py
compass/api_client/api/uniswap_v3_api.py
compass/api_client/api/universal_api.py
compass/api_client/models/__init__.py
compass/api_client/models/aave_asset_price_response.py
compass/api_client/models/aave_borrow_request.py
compass/api_client/models/aave_get_asset_price_request.py
compass/api_client/models/aave_get_liquidity_change_request.py
compass/api_client/models/aave_get_user_position_per_token_request.py
compass/api_client/models/aave_get_user_position_summary_request.py
compass/api_client/models/aave_liquidity_change_response.py
compass/api_client/models/aave_repay_request.py
compass/api_client/models/aave_supply_request.py
compass/api_client/models/aave_user_position_per_token_response.py
compass/api_client/models/aave_user_position_summary_response.py
compass/api_client/models/aave_withdraw_request.py
compass/api_client/models/address_request.py
compass/api_client/models/address_response.py
compass/api_client/models/aerodrome_lp_positions_response.py
compass/api_client/models/aerodrome_position.py
compass/api_client/models/aerodrome_slipstream_buy_exactly_request.py
compass/api_client/models/aerodrome_slipstream_get_liquidity_provision_positions_request.py
compass/api_client/models/aerodrome_slipstream_get_pool_price_request.py
compass/api_client/models/aerodrome_slipstream_increase_liquidity_provision_request.py
compass_api_client-1.0.191.dist-info/METADATA
compass_api_client-1.0.191.dist-info/WHEEL
compass_api_client-1.0.191.dist-info/top_level.txt
compass_api_client-1.0.191.dist-info/RECORD
